<?xml version="1.0" encoding="utf-8"?>
<annotation>
  <filename>All/Rainy_02.mp4/Rainy_02.mp4_04000.jpg</filename>
  <size>
    <width>1920</width>
    <height>1080</height>
    <depth>3</depth>
  </size>
  <object>
    <name>vehicle</name>
    <bndbox>
      <xmin>690</xmin>
      <ymin>569</ymin>
      <xmax>788</xmax>
      <ymax>646</ymax>
    </bndbox>
  </object>
  <object>
    <name>rider</name>
    <bndbox>
      <xmin>665</xmin>
      <ymin>602</ymin>
      <xmax>710</xmax>
      <ymax>726</ymax>
    </bndbox>
  </object>
  <object>
    <name>rider</name>
    <bndbox>
      <xmin>536</xmin>
      <ymin>578</ymin>
      <xmax>627</xmax>
      <ymax>837</ymax>
    </bndbox>
  </object>
  <object>
    <name>vehicle</name>
    <bndbox>
      <xmin>776</xmin>
      <ymin>590</ymin>
      <xmax>1026</xmax>
      <ymax>784</ymax>
    </bndbox>
  </object>
  <object>
    <name>vehicle</name>
    <bndbox>
      <xmin>315</xmin>
      <ymin>598</ymin>
      <xmax>612</xmax>
      <ymax>778</ymax>
    </bndbox>
  </object>
  <object>
    <name>pedestrian</name>
    <bndbox>
      <xmin>1215</xmin>
      <ymin>612</ymin>
      <xmax>1256</xmax>
      <ymax>708</ymax>
    </bndbox>
  </object>
  <object>
    <name>vehicle</name>
    <bndbox>
      <xmin>2</xmin>
      <ymin>554</ymin>
      <xmax>269</xmax>
      <ymax>946</ymax>
    </bndbox>
  </object>
  <object>
    <name>rider</name>
    <bndbox>
      <xmin>705</xmin>
      <ymin>604</ymin>
      <xmax>752</xmax>
      <ymax>727</ymax>
    </bndbox>
  </object>
  <object>
    <name>vehicle</name>
    <bndbox>
      <xmin>835</xmin>
      <ymin>594</ymin>
      <xmax>1194</xmax>
      <ymax>898</ymax>
    </bndbox>
  </object>
  <object>
    <name>rider</name>
    <bndbox>
      <xmin>601</xmin>
      <ymin>579</ymin>
      <xmax>698</xmax>
      <ymax>775</ymax>
    </bndbox>
  </object>
</annotation>
