<?xml version="1.0" encoding="utf-8"?>
<annotation>
  <filename>All/Rainy_02.mp4/Rainy_02.mp4_04248.jpg</filename>
  <size>
    <width>1920</width>
    <height>1080</height>
    <depth>3</depth>
  </size>
  <object>
    <name>vehicle</name>
    <bndbox>
      <xmin>776</xmin>
      <ymin>590</ymin>
      <xmax>1026</xmax>
      <ymax>784</ymax>
    </bndbox>
  </object>
  <object>
    <name>rider</name>
    <bndbox>
      <xmin>650</xmin>
      <ymin>580</ymin>
      <xmax>732</xmax>
      <ymax>769</ymax>
    </bndbox>
  </object>
  <object>
    <name>rider</name>
    <bndbox>
      <xmin>181</xmin>
      <ymin>496</ymin>
      <xmax>411</xmax>
      <ymax>969</ymax>
    </bndbox>
  </object>
  <object>
    <name>vehicle</name>
    <bndbox>
      <xmin>418</xmin>
      <ymin>602</ymin>
      <xmax>644</xmax>
      <ymax>760</ymax>
    </bndbox>
  </object>
  <object>
    <name>rider</name>
    <bndbox>
      <xmin>740</xmin>
      <ymin>612</ymin>
      <xmax>787</xmax>
      <ymax>724</ymax>
    </bndbox>
  </object>
  <object>
    <name>rider</name>
    <bndbox>
      <xmin>534</xmin>
      <ymin>580</ymin>
      <xmax>667</xmax>
      <ymax>826</ymax>
    </bndbox>
  </object>
  <object>
    <name>vehicle</name>
    <bndbox>
      <xmin>835</xmin>
      <ymin>594</ymin>
      <xmax>1194</xmax>
      <ymax>898</ymax>
    </bndbox>
  </object>
  <object>
    <name>rider</name>
    <bndbox>
      <xmin>709</xmin>
      <ymin>603</ymin>
      <xmax>771</xmax>
      <ymax>753</ymax>
    </bndbox>
  </object>
  <object>
    <name>vehicle</name>
    <bndbox>
      <xmin>1</xmin>
      <ymin>297</ymin>
      <xmax>384</xmax>
      <ymax>813</ymax>
    </bndbox>
  </object>
  <object>
    <name>rider</name>
    <bndbox>
      <xmin>322</xmin>
      <ymin>559</ymin>
      <xmax>466</xmax>
      <ymax>829</ymax>
    </bndbox>
  </object>
</annotation>
