<?xml version="1.0" encoding="utf-8"?>
<annotation>
  <filename>All/Cityscape_04.mp4/Cityscape_04.mp4_05553.jpg</filename>
  <size>
    <width>1920</width>
    <height>1080</height>
    <depth>3</depth>
  </size>
  <object>
    <name>vehicle</name>
    <bndbox>
      <xmin>1</xmin>
      <ymin>272</ymin>
      <xmax>90</xmax>
      <ymax>482</ymax>
    </bndbox>
  </object>
  <object>
    <name>rider</name>
    <bndbox>
      <xmin>1173</xmin>
      <ymin>277</ymin>
      <xmax>1235</xmax>
      <ymax>444</ymax>
    </bndbox>
  </object>
  <object>
    <name>rider</name>
    <bndbox>
      <xmin>604</xmin>
      <ymin>282</ymin>
      <xmax>637</xmax>
      <ymax>347</ymax>
    </bndbox>
  </object>
  <object>
    <name>rider</name>
    <bndbox>
      <xmin>1197</xmin>
      <ymin>262</ymin>
      <xmax>1277</xmax>
      <ymax>476</ymax>
    </bndbox>
  </object>
  <object>
    <name>pedestrian</name>
    <bndbox>
      <xmin>487</xmin>
      <ymin>261</ymin>
      <xmax>507</xmax>
      <ymax>313</ymax>
    </bndbox>
  </object>
  <object>
    <name>vehicle</name>
    <bndbox>
      <xmin>682</xmin>
      <ymin>286</ymin>
      <xmax>778</xmax>
      <ymax>346</ymax>
    </bndbox>
  </object>
  <object>
    <name>rider</name>
    <bndbox>
      <xmin>988</xmin>
      <ymin>285</ymin>
      <xmax>1038</xmax>
      <ymax>373</ymax>
    </bndbox>
  </object>
  <object>
    <name>rider</name>
    <bndbox>
      <xmin>667</xmin>
      <ymin>289</ymin>
      <xmax>688</xmax>
      <ymax>325</ymax>
    </bndbox>
  </object>
  <object>
    <name>vehicle</name>
    <bndbox>
      <xmin>738</xmin>
      <ymin>231</ymin>
      <xmax>967</xmax>
      <ymax>456</ymax>
    </bndbox>
  </object>
  <object>
    <name>vehicle</name>
    <bndbox>
      <xmin>1119</xmin>
      <ymin>278</ymin>
      <xmax>1212</xmax>
      <ymax>369</ymax>
    </bndbox>
  </object>
  <object>
    <name>vehicle</name>
    <bndbox>
      <xmin>1529</xmin>
      <ymin>332</ymin>
      <xmax>1920</xmax>
      <ymax>532</ymax>
    </bndbox>
  </object>
  <object>
    <name>rider</name>
    <bndbox>
      <xmin>624</xmin>
      <ymin>282</ymin>
      <xmax>650</xmax>
      <ymax>343</ymax>
    </bndbox>
  </object>
</annotation>
