<?xml version="1.0" encoding="utf-8"?>
<annotation>
  <filename>All/Cityscape_04.mp4/Cityscape_04.mp4_00524.jpg</filename>
  <size>
    <width>1920</width>
    <height>1080</height>
    <depth>3</depth>
  </size>
  <object>
    <name>vehicle</name>
    <bndbox>
      <xmin>959</xmin>
      <ymin>281</ymin>
      <xmax>1017</xmax>
      <ymax>335</ymax>
    </bndbox>
  </object>
  <object>
    <name>vehicle</name>
    <bndbox>
      <xmin>1036</xmin>
      <ymin>288</ymin>
      <xmax>1154</xmax>
      <ymax>375</ymax>
    </bndbox>
  </object>
  <object>
    <name>vehicle</name>
    <bndbox>
      <xmin>1042</xmin>
      <ymin>295</ymin>
      <xmax>1156</xmax>
      <ymax>379</ymax>
    </bndbox>
  </object>
  <object>
    <name>vehicle</name>
    <bndbox>
      <xmin>277</xmin>
      <ymin>297</ymin>
      <xmax>393</xmax>
      <ymax>352</ymax>
    </bndbox>
  </object>
  <object>
    <name>vehicle</name>
    <bndbox>
      <xmin>871</xmin>
      <ymin>274</ymin>
      <xmax>956</xmax>
      <ymax>352</ymax>
    </bndbox>
  </object>
  <object>
    <name>vehicle</name>
    <bndbox>
      <xmin>872</xmin>
      <ymin>276</ymin>
      <xmax>966</xmax>
      <ymax>361</ymax>
    </bndbox>
  </object>
  <object>
    <name>vehicle</name>
    <bndbox>
      <xmin>159</xmin>
      <ymin>302</ymin>
      <xmax>293</xmax>
      <ymax>383</ymax>
    </bndbox>
  </object>
  <object>
    <name>vehicle</name>
    <bndbox>
      <xmin>1237</xmin>
      <ymin>276</ymin>
      <xmax>1639</xmax>
      <ymax>532</ymax>
    </bndbox>
  </object>
  <object>
    <name>vehicle</name>
    <bndbox>
      <xmin>1</xmin>
      <ymin>323</ymin>
      <xmax>124</xmax>
      <ymax>410</ymax>
    </bndbox>
  </object>
  <object>
    <name>vehicle</name>
    <bndbox>
      <xmin>505</xmin>
      <ymin>268</ymin>
      <xmax>726</xmax>
      <ymax>392</ymax>
    </bndbox>
  </object>
  <object>
    <name>vehicle</name>
    <bndbox>
      <xmin>1237</xmin>
      <ymin>276</ymin>
      <xmax>1639</xmax>
      <ymax>532</ymax>
    </bndbox>
  </object>
  <object>
    <name>vehicle</name>
    <bndbox>
      <xmin>280</xmin>
      <ymin>302</ymin>
      <xmax>396</xmax>
      <ymax>358</ymax>
    </bndbox>
  </object>
  <object>
    <name>vehicle</name>
    <bndbox>
      <xmin>1</xmin>
      <ymin>323</ymin>
      <xmax>124</xmax>
      <ymax>410</ymax>
    </bndbox>
  </object>
  <object>
    <name>vehicle</name>
    <bndbox>
      <xmin>959</xmin>
      <ymin>280</ymin>
      <xmax>1015</xmax>
      <ymax>332</ymax>
    </bndbox>
  </object>
  <object>
    <name>vehicle</name>
    <bndbox>
      <xmin>503</xmin>
      <ymin>267</ymin>
      <xmax>727</xmax>
      <ymax>393</ymax>
    </bndbox>
  </object>
  <object>
    <name>vehicle</name>
    <bndbox>
      <xmin>158</xmin>
      <ymin>304</ymin>
      <xmax>292</xmax>
      <ymax>386</ymax>
    </bndbox>
  </object>
</annotation>
