<?xml version="1.0" encoding="utf-8"?>
<annotation>
  <filename>All/Cityscape_04.mp4/Cityscape_04.mp4_06734.jpg</filename>
  <size>
    <width>1920</width>
    <height>1080</height>
    <depth>3</depth>
  </size>
  <object>
    <name>vehicle</name>
    <bndbox>
      <xmin>1151</xmin>
      <ymin>302</ymin>
      <xmax>1389</xmax>
      <ymax>448</ymax>
    </bndbox>
  </object>
  <object>
    <name>pedestrian</name>
    <bndbox>
      <xmin>644</xmin>
      <ymin>277</ymin>
      <xmax>666</xmax>
      <ymax>343</ymax>
    </bndbox>
  </object>
  <object>
    <name>vehicle</name>
    <bndbox>
      <xmin>478</xmin>
      <ymin>282</ymin>
      <xmax>586</xmax>
      <ymax>359</ymax>
    </bndbox>
  </object>
  <object>
    <name>pedestrian</name>
    <bndbox>
      <xmin>1784</xmin>
      <ymin>278</ymin>
      <xmax>1905</xmax>
      <ymax>678</ymax>
    </bndbox>
  </object>
  <object>
    <name>pedestrian</name>
    <bndbox>
      <xmin>1140</xmin>
      <ymin>271</ymin>
      <xmax>1179</xmax>
      <ymax>395</ymax>
    </bndbox>
  </object>
  <object>
    <name>vehicle</name>
    <bndbox>
      <xmin>814</xmin>
      <ymin>278</ymin>
      <xmax>966</xmax>
      <ymax>407</ymax>
    </bndbox>
  </object>
  <object>
    <name>vehicle</name>
    <bndbox>
      <xmin>1</xmin>
      <ymin>16</ymin>
      <xmax>571</xmax>
      <ymax>724</ymax>
    </bndbox>
  </object>
  <object>
    <name>rider</name>
    <bndbox>
      <xmin>992</xmin>
      <ymin>242</ymin>
      <xmax>1118</xmax>
      <ymax>508</ymax>
    </bndbox>
  </object>
  <object>
    <name>vehicle</name>
    <bndbox>
      <xmin>654</xmin>
      <ymin>280</ymin>
      <xmax>753</xmax>
      <ymax>354</ymax>
    </bndbox>
  </object>
</annotation>
