<?xml version="1.0" encoding="utf-8"?>
<annotation>
  <filename>All/Cityscape_04.mp4/Cityscape_04.mp4_04257.jpg</filename>
  <size>
    <width>1920</width>
    <height>1080</height>
    <depth>3</depth>
  </size>
  <object>
    <name>vehicle</name>
    <bndbox>
      <xmin>577</xmin>
      <ymin>282</ymin>
      <xmax>686</xmax>
      <ymax>367</ymax>
    </bndbox>
  </object>
  <object>
    <name>vehicle</name>
    <bndbox>
      <xmin>1734</xmin>
      <ymin>312</ymin>
      <xmax>1920</xmax>
      <ymax>720</ymax>
    </bndbox>
  </object>
  <object>
    <name>vehicle</name>
    <bndbox>
      <xmin>346</xmin>
      <ymin>299</ymin>
      <xmax>464</xmax>
      <ymax>378</ymax>
    </bndbox>
  </object>
  <object>
    <name>vehicle</name>
    <bndbox>
      <xmin>865</xmin>
      <ymin>254</ymin>
      <xmax>944</xmax>
      <ymax>354</ymax>
    </bndbox>
  </object>
  <object>
    <name>vehicle</name>
    <bndbox>
      <xmin>484</xmin>
      <ymin>290</ymin>
      <xmax>576</xmax>
      <ymax>361</ymax>
    </bndbox>
  </object>
  <object>
    <name>vehicle</name>
    <bndbox>
      <xmin>746</xmin>
      <ymin>254</ymin>
      <xmax>910</xmax>
      <ymax>410</ymax>
    </bndbox>
  </object>
</annotation>
