<?xml version="1.0" encoding="utf-8"?>
<annotation>
  <filename>All/Cityscape_04.mp4/Cityscape_04.mp4_05987.jpg</filename>
  <size>
    <width>1920</width>
    <height>1080</height>
    <depth>3</depth>
  </size>
  <object>
    <name>rider</name>
    <bndbox>
      <xmin>1152</xmin>
      <ymin>296</ymin>
      <xmax>1183</xmax>
      <ymax>373</ymax>
    </bndbox>
  </object>
  <object>
    <name>rider</name>
    <bndbox>
      <xmin>1123</xmin>
      <ymin>296</ymin>
      <xmax>1149</xmax>
      <ymax>359</ymax>
    </bndbox>
  </object>
  <object>
    <name>vehicle</name>
    <bndbox>
      <xmin>892</xmin>
      <ymin>246</ymin>
      <xmax>1121</xmax>
      <ymax>458</ymax>
    </bndbox>
  </object>
  <object>
    <name>vehicle</name>
    <bndbox>
      <xmin>644</xmin>
      <ymin>199</ymin>
      <xmax>902</xmax>
      <ymax>386</ymax>
    </bndbox>
  </object>
  <object>
    <name>vehicle</name>
    <bndbox>
      <xmin>1319</xmin>
      <ymin>313</ymin>
      <xmax>1629</xmax>
      <ymax>488</ymax>
    </bndbox>
  </object>
</annotation>
