<?xml version="1.0" encoding="utf-8"?>
<annotation>
  <filename>All/Rainy_01.mp4/Rainy_01.mp4_04086.jpg</filename>
  <size>
    <width>1920</width>
    <height>1080</height>
    <depth>3</depth>
  </size>
  <object>
    <name>vehicle</name>
    <bndbox>
      <xmin>1291</xmin>
      <ymin>1</ymin>
      <xmax>1882</xmax>
      <ymax>497</ymax>
    </bndbox>
  </object>
  <object>
    <name>vehicle</name>
    <bndbox>
      <xmin>775</xmin>
      <ymin>280</ymin>
      <xmax>836</xmax>
      <ymax>342</ymax>
    </bndbox>
  </object>
  <object>
    <name>vehicle</name>
    <bndbox>
      <xmin>1094</xmin>
      <ymin>263</ymin>
      <xmax>1176</xmax>
      <ymax>349</ymax>
    </bndbox>
  </object>
  <object>
    <name>rider</name>
    <bndbox>
      <xmin>1163</xmin>
      <ymin>253</ymin>
      <xmax>1340</xmax>
      <ymax>564</ymax>
    </bndbox>
  </object>
  <object>
    <name>vehicle</name>
    <bndbox>
      <xmin>932</xmin>
      <ymin>199</ymin>
      <xmax>1067</xmax>
      <ymax>368</ymax>
    </bndbox>
  </object>
  <object>
    <name>vehicle</name>
    <bndbox>
      <xmin>831</xmin>
      <ymin>259</ymin>
      <xmax>901</xmax>
      <ymax>334</ymax>
    </bndbox>
  </object>
  <object>
    <name>rider</name>
    <bndbox>
      <xmin>912</xmin>
      <ymin>287</ymin>
      <xmax>955</xmax>
      <ymax>390</ymax>
    </bndbox>
  </object>
</annotation>
