<?xml version="1.0" encoding="utf-8"?>
<annotation>
  <filename>All/Cityscape_05.mp4/Cityscape_05.mp4_01300.jpg</filename>
  <size>
    <width>1920</width>
    <height>1080</height>
    <depth>3</depth>
  </size>
  <object>
    <name>vehicle</name>
    <bndbox>
      <xmin>1223</xmin>
      <ymin>293</ymin>
      <xmax>1681</xmax>
      <ymax>579</ymax>
    </bndbox>
  </object>
  <object>
    <name>rider</name>
    <bndbox>
      <xmin>468</xmin>
      <ymin>253</ymin>
      <xmax>553</xmax>
      <ymax>444</ymax>
    </bndbox>
  </object>
  <object>
    <name>vehicle</name>
    <bndbox>
      <xmin>481</xmin>
      <ymin>262</ymin>
      <xmax>607</xmax>
      <ymax>352</ymax>
    </bndbox>
  </object>
  <object>
    <name>vehicle</name>
    <bndbox>
      <xmin>987</xmin>
      <ymin>295</ymin>
      <xmax>1145</xmax>
      <ymax>425</ymax>
    </bndbox>
  </object>
  <object>
    <name>pedestrian</name>
    <bndbox>
      <xmin>209</xmin>
      <ymin>268</ymin>
      <xmax>241</xmax>
      <ymax>370</ymax>
    </bndbox>
  </object>
  <object>
    <name>vehicle</name>
    <bndbox>
      <xmin>1101</xmin>
      <ymin>301</ymin>
      <xmax>1331</xmax>
      <ymax>464</ymax>
    </bndbox>
  </object>
  <object>
    <name>vehicle</name>
    <bndbox>
      <xmin>594</xmin>
      <ymin>68</ymin>
      <xmax>1094</xmax>
      <ymax>635</ymax>
    </bndbox>
  </object>
  <object>
    <name>pedestrian</name>
    <bndbox>
      <xmin>343</xmin>
      <ymin>269</ymin>
      <xmax>381</xmax>
      <ymax>379</ymax>
    </bndbox>
  </object>
  <object>
    <name>pedestrian</name>
    <bndbox>
      <xmin>444</xmin>
      <ymin>274</ymin>
      <xmax>489</xmax>
      <ymax>370</ymax>
    </bndbox>
  </object>
</annotation>
