<?xml version="1.0" encoding="utf-8"?>
<annotation>
  <filename>All/Cityscape_05.mp4/Cityscape_05.mp4_02056.jpg</filename>
  <size>
    <width>1920</width>
    <height>1080</height>
    <depth>3</depth>
  </size>
  <object>
    <name>pedestrian</name>
    <bndbox>
      <xmin>1107</xmin>
      <ymin>247</ymin>
      <xmax>1180</xmax>
      <ymax>461</ymax>
    </bndbox>
  </object>
  <object>
    <name>pedestrian</name>
    <bndbox>
      <xmin>1168</xmin>
      <ymin>251</ymin>
      <xmax>1264</xmax>
      <ymax>506</ymax>
    </bndbox>
  </object>
  <object>
    <name>rider</name>
    <bndbox>
      <xmin>1073</xmin>
      <ymin>277</ymin>
      <xmax>1106</xmax>
      <ymax>346</ymax>
    </bndbox>
  </object>
  <object>
    <name>vehicle</name>
    <bndbox>
      <xmin>3</xmin>
      <ymin>284</ymin>
      <xmax>343</xmax>
      <ymax>510</ymax>
    </bndbox>
  </object>
  <object>
    <name>vehicle</name>
    <bndbox>
      <xmin>1180</xmin>
      <ymin>275</ymin>
      <xmax>1445</xmax>
      <ymax>476</ymax>
    </bndbox>
  </object>
  <object>
    <name>vehicle</name>
    <bndbox>
      <xmin>1289</xmin>
      <ymin>197</ymin>
      <xmax>1876</xmax>
      <ymax>664</ymax>
    </bndbox>
  </object>
  <object>
    <name>vehicle</name>
    <bndbox>
      <xmin>128</xmin>
      <ymin>297</ymin>
      <xmax>440</xmax>
      <ymax>435</ymax>
    </bndbox>
  </object>
  <object>
    <name>vehicle</name>
    <bndbox>
      <xmin>691</xmin>
      <ymin>126</ymin>
      <xmax>1043</xmax>
      <ymax>549</ymax>
    </bndbox>
  </object>
  <object>
    <name>vehicle</name>
    <bndbox>
      <xmin>431</xmin>
      <ymin>274</ymin>
      <xmax>588</xmax>
      <ymax>407</ymax>
    </bndbox>
  </object>
  <object>
    <name>vehicle</name>
    <bndbox>
      <xmin>675</xmin>
      <ymin>180</ymin>
      <xmax>881</xmax>
      <ymax>367</ymax>
    </bndbox>
  </object>
</annotation>
