<?xml version="1.0" encoding="utf-8"?>
<annotation>
  <filename>All/Cityscape_05.mp4/Cityscape_05.mp4_08878.jpg</filename>
  <size>
    <width>1920</width>
    <height>1080</height>
    <depth>3</depth>
  </size>
  <object>
    <name>vehicle</name>
    <bndbox>
      <xmin>2</xmin>
      <ymin>271</ymin>
      <xmax>452</xmax>
      <ymax>545</ymax>
    </bndbox>
  </object>
  <object>
    <name>vehicle</name>
    <bndbox>
      <xmin>605</xmin>
      <ymin>23</ymin>
      <xmax>1188</xmax>
      <ymax>572</ymax>
    </bndbox>
  </object>
  <object>
    <name>pedestrian</name>
    <bndbox>
      <xmin>1717</xmin>
      <ymin>226</ymin>
      <xmax>1805</xmax>
      <ymax>476</ymax>
    </bndbox>
  </object>
</annotation>
