<?xml version="1.0" encoding="utf-8"?>
<annotation>
  <filename>All/Cityscape_05.mp4/Cityscape_05.mp4_04541.jpg</filename>
  <size>
    <width>1920</width>
    <height>1080</height>
    <depth>3</depth>
  </size>
  <object>
    <name>vehicle</name>
    <bndbox>
      <xmin>1411</xmin>
      <ymin>301</ymin>
      <xmax>1719</xmax>
      <ymax>531</ymax>
    </bndbox>
  </object>
  <object>
    <name>pedestrian</name>
    <bndbox>
      <xmin>939</xmin>
      <ymin>276</ymin>
      <xmax>971</xmax>
      <ymax>356</ymax>
    </bndbox>
  </object>
  <object>
    <name>vehicle</name>
    <bndbox>
      <xmin>586</xmin>
      <ymin>279</ymin>
      <xmax>714</xmax>
      <ymax>383</ymax>
    </bndbox>
  </object>
  <object>
    <name>vehicle</name>
    <bndbox>
      <xmin>74</xmin>
      <ymin>231</ymin>
      <xmax>447</xmax>
      <ymax>524</ymax>
    </bndbox>
  </object>
  <object>
    <name>pedestrian</name>
    <bndbox>
      <xmin>1021</xmin>
      <ymin>271</ymin>
      <xmax>1054</xmax>
      <ymax>369</ymax>
    </bndbox>
  </object>
  <object>
    <name>rider</name>
    <bndbox>
      <xmin>872</xmin>
      <ymin>271</ymin>
      <xmax>928</xmax>
      <ymax>391</ymax>
    </bndbox>
  </object>
  <object>
    <name>pedestrian</name>
    <bndbox>
      <xmin>969</xmin>
      <ymin>267</ymin>
      <xmax>999</xmax>
      <ymax>362</ymax>
    </bndbox>
  </object>
  <object>
    <name>pedestrian</name>
    <bndbox>
      <xmin>1005</xmin>
      <ymin>272</ymin>
      <xmax>1038</xmax>
      <ymax>373</ymax>
    </bndbox>
  </object>
  <object>
    <name>vehicle</name>
    <bndbox>
      <xmin>1077</xmin>
      <ymin>292</ymin>
      <xmax>1205</xmax>
      <ymax>382</ymax>
    </bndbox>
  </object>
  <object>
    <name>pedestrian</name>
    <bndbox>
      <xmin>1745</xmin>
      <ymin>267</ymin>
      <xmax>1911</xmax>
      <ymax>671</ymax>
    </bndbox>
  </object>
  <object>
    <name>vehicle</name>
    <bndbox>
      <xmin>1182</xmin>
      <ymin>297</ymin>
      <xmax>1386</xmax>
      <ymax>408</ymax>
    </bndbox>
  </object>
  <object>
    <name>pedestrian</name>
    <bndbox>
      <xmin>1058</xmin>
      <ymin>284</ymin>
      <xmax>1089</xmax>
      <ymax>372</ymax>
    </bndbox>
  </object>
</annotation>
