<?xml version="1.0" encoding="utf-8"?>
<annotation>
  <filename>All/Cityscape_05.mp4/Cityscape_05.mp4_01271.jpg</filename>
  <size>
    <width>1920</width>
    <height>1080</height>
    <depth>3</depth>
  </size>
  <object>
    <name>vehicle</name>
    <bndbox>
      <xmin>1197</xmin>
      <ymin>299</ymin>
      <xmax>1600</xmax>
      <ymax>553</ymax>
    </bndbox>
  </object>
  <object>
    <name>rider</name>
    <bndbox>
      <xmin>578</xmin>
      <ymin>265</ymin>
      <xmax>640</xmax>
      <ymax>393</ymax>
    </bndbox>
  </object>
  <object>
    <name>vehicle</name>
    <bndbox>
      <xmin>496</xmin>
      <ymin>266</ymin>
      <xmax>607</xmax>
      <ymax>352</ymax>
    </bndbox>
  </object>
  <object>
    <name>vehicle</name>
    <bndbox>
      <xmin>985</xmin>
      <ymin>295</ymin>
      <xmax>1128</xmax>
      <ymax>415</ymax>
    </bndbox>
  </object>
  <object>
    <name>pedestrian</name>
    <bndbox>
      <xmin>231</xmin>
      <ymin>273</ymin>
      <xmax>261</xmax>
      <ymax>372</ymax>
    </bndbox>
  </object>
  <object>
    <name>vehicle</name>
    <bndbox>
      <xmin>1083</xmin>
      <ymin>304</ymin>
      <xmax>1315</xmax>
      <ymax>456</ymax>
    </bndbox>
  </object>
  <object>
    <name>vehicle</name>
    <bndbox>
      <xmin>628</xmin>
      <ymin>97</ymin>
      <xmax>1075</xmax>
      <ymax>610</ymax>
    </bndbox>
  </object>
  <object>
    <name>pedestrian</name>
    <bndbox>
      <xmin>359</xmin>
      <ymin>271</ymin>
      <xmax>398</xmax>
      <ymax>378</ymax>
    </bndbox>
  </object>
  <object>
    <name>pedestrian</name>
    <bndbox>
      <xmin>462</xmin>
      <ymin>281</ymin>
      <xmax>505</xmax>
      <ymax>374</ymax>
    </bndbox>
  </object>
  <object>
    <name>rider</name>
    <bndbox>
      <xmin>1851</xmin>
      <ymin>357</ymin>
      <xmax>1920</xmax>
      <ymax>545</ymax>
    </bndbox>
  </object>
</annotation>
