<?xml version="1.0" encoding="utf-8"?>
<annotation>
  <filename>All/Cityscape_03.mp4/Cityscape_03.mp4_00016.jpg</filename>
  <size>
    <width>1920</width>
    <height>1080</height>
    <depth>3</depth>
  </size>
  <object>
    <name>rider</name>
    <bndbox>
      <xmin>1527</xmin>
      <ymin>485</ymin>
      <xmax>1901</xmax>
      <ymax>1063</ymax>
    </bndbox>
  </object>
  <object>
    <name>rider</name>
    <bndbox>
      <xmin>165</xmin>
      <ymin>556</ymin>
      <xmax>492</xmax>
      <ymax>999</ymax>
    </bndbox>
  </object>
  <object>
    <name>vehicle</name>
    <bndbox>
      <xmin>44</xmin>
      <ymin>591</ymin>
      <xmax>571</xmax>
      <ymax>933</ymax>
    </bndbox>
  </object>
  <object>
    <name>rider</name>
    <bndbox>
      <xmin>556</xmin>
      <ymin>613</ymin>
      <xmax>702</xmax>
      <ymax>932</ymax>
    </bndbox>
  </object>
  <object>
    <name>rider</name>
    <bndbox>
      <xmin>1247</xmin>
      <ymin>607</ymin>
      <xmax>1448</xmax>
      <ymax>995</ymax>
    </bndbox>
  </object>
  <object>
    <name>pedestrian</name>
    <bndbox>
      <xmin>1634</xmin>
      <ymin>586</ymin>
      <xmax>1675</xmax>
      <ymax>678</ymax>
    </bndbox>
  </object>
  <object>
    <name>pedestrian</name>
    <bndbox>
      <xmin>1651</xmin>
      <ymin>580</ymin>
      <xmax>1695</xmax>
      <ymax>666</ymax>
    </bndbox>
  </object>
  <object>
    <name>vehicle</name>
    <bndbox>
      <xmin>570</xmin>
      <ymin>601</ymin>
      <xmax>1137</xmax>
      <ymax>1031</ymax>
    </bndbox>
  </object>
  <object>
    <name>rider</name>
    <bndbox>
      <xmin>1068</xmin>
      <ymin>649</ymin>
      <xmax>1170</xmax>
      <ymax>861</ymax>
    </bndbox>
  </object>
</annotation>
