<?xml version="1.0" encoding="utf-8"?>
<annotation>
  <filename>All/Cityscape_03.mp4/Cityscape_03.mp4_00033.jpg</filename>
  <size>
    <width>1920</width>
    <height>1080</height>
    <depth>3</depth>
  </size>
  <object>
    <name>rider</name>
    <bndbox>
      <xmin>1431</xmin>
      <ymin>545</ymin>
      <xmax>1739</xmax>
      <ymax>1049</ymax>
    </bndbox>
  </object>
  <object>
    <name>vehicle</name>
    <bndbox>
      <xmin>557</xmin>
      <ymin>662</ymin>
      <xmax>777</xmax>
      <ymax>804</ymax>
    </bndbox>
  </object>
  <object>
    <name>rider</name>
    <bndbox>
      <xmin>332</xmin>
      <ymin>586</ymin>
      <xmax>605</xmax>
      <ymax>990</ymax>
    </bndbox>
  </object>
  <object>
    <name>vehicle</name>
    <bndbox>
      <xmin>42</xmin>
      <ymin>591</ymin>
      <xmax>572</xmax>
      <ymax>932</ymax>
    </bndbox>
  </object>
  <object>
    <name>rider</name>
    <bndbox>
      <xmin>1201</xmin>
      <ymin>618</ymin>
      <xmax>1401</xmax>
      <ymax>968</ymax>
    </bndbox>
  </object>
  <object>
    <name>vehicle</name>
    <bndbox>
      <xmin>568</xmin>
      <ymin>601</ymin>
      <xmax>1138</xmax>
      <ymax>1033</ymax>
    </bndbox>
  </object>
  <object>
    <name>rider</name>
    <bndbox>
      <xmin>1063</xmin>
      <ymin>651</ymin>
      <xmax>1159</xmax>
      <ymax>853</ymax>
    </bndbox>
  </object>
</annotation>
