<?xml version="1.0" encoding="utf-8"?>
<annotation>
  <filename>All/Cityscape_03.mp4/Cityscape_03.mp4_01983.jpg</filename>
  <size>
    <width>1920</width>
    <height>1080</height>
    <depth>3</depth>
  </size>
  <object>
    <name>pedestrian</name>
    <bndbox>
      <xmin>1369</xmin>
      <ymin>667</ymin>
      <xmax>1396</xmax>
      <ymax>719</ymax>
    </bndbox>
  </object>
  <object>
    <name>vehicle</name>
    <bndbox>
      <xmin>969</xmin>
      <ymin>652</ymin>
      <xmax>1175</xmax>
      <ymax>842</ymax>
    </bndbox>
  </object>
  <object>
    <name>pedestrian</name>
    <bndbox>
      <xmin>1437</xmin>
      <ymin>635</ymin>
      <xmax>1475</xmax>
      <ymax>756</ymax>
    </bndbox>
  </object>
  <object>
    <name>vehicle</name>
    <bndbox>
      <xmin>1463</xmin>
      <ymin>647</ymin>
      <xmax>1643</xmax>
      <ymax>711</ymax>
    </bndbox>
  </object>
  <object>
    <name>vehicle</name>
    <bndbox>
      <xmin>887</xmin>
      <ymin>696</ymin>
      <xmax>1008</xmax>
      <ymax>737</ymax>
    </bndbox>
  </object>
</annotation>
