<?xml version="1.0" encoding="utf-8"?>
<annotation>
  <filename>All/Cityscape_03.mp4/Cityscape_03.mp4_02626.jpg</filename>
  <size>
    <width>1920</width>
    <height>1080</height>
    <depth>3</depth>
  </size>
  <object>
    <name>vehicle</name>
    <bndbox>
      <xmin>1134</xmin>
      <ymin>694</ymin>
      <xmax>1257</xmax>
      <ymax>757</ymax>
    </bndbox>
  </object>
  <object>
    <name>pedestrian</name>
    <bndbox>
      <xmin>606</xmin>
      <ymin>672</ymin>
      <xmax>641</xmax>
      <ymax>761</ymax>
    </bndbox>
  </object>
  <object>
    <name>vehicle</name>
    <bndbox>
      <xmin>1434</xmin>
      <ymin>677</ymin>
      <xmax>1610</xmax>
      <ymax>749</ymax>
    </bndbox>
  </object>
  <object>
    <name>vehicle</name>
    <bndbox>
      <xmin>1295</xmin>
      <ymin>689</ymin>
      <xmax>1385</xmax>
      <ymax>752</ymax>
    </bndbox>
  </object>
  <object>
    <name>pedestrian</name>
    <bndbox>
      <xmin>1074</xmin>
      <ymin>694</ymin>
      <xmax>1105</xmax>
      <ymax>763</ymax>
    </bndbox>
  </object>
  <object>
    <name>vehicle</name>
    <bndbox>
      <xmin>1230</xmin>
      <ymin>696</ymin>
      <xmax>1312</xmax>
      <ymax>747</ymax>
    </bndbox>
  </object>
  <object>
    <name>vehicle</name>
    <bndbox>
      <xmin>1325</xmin>
      <ymin>687</ymin>
      <xmax>1583</xmax>
      <ymax>788</ymax>
    </bndbox>
  </object>
</annotation>
