<?xml version="1.0" encoding="utf-8"?>
<annotation>
  <filename>All/Cityscape_03.mp4/Cityscape_03.mp4_00903.jpg</filename>
  <size>
    <width>1920</width>
    <height>1080</height>
    <depth>3</depth>
  </size>
  <object>
    <name>vehicle</name>
    <bndbox>
      <xmin>772</xmin>
      <ymin>693</ymin>
      <xmax>806</xmax>
      <ymax>717</ymax>
    </bndbox>
  </object>
  <object>
    <name>vehicle</name>
    <bndbox>
      <xmin>1062</xmin>
      <ymin>697</ymin>
      <xmax>1143</xmax>
      <ymax>752</ymax>
    </bndbox>
  </object>
  <object>
    <name>vehicle</name>
    <bndbox>
      <xmin>1163</xmin>
      <ymin>679</ymin>
      <xmax>1330</xmax>
      <ymax>796</ymax>
    </bndbox>
  </object>
  <object>
    <name>rider</name>
    <bndbox>
      <xmin>919</xmin>
      <ymin>680</ymin>
      <xmax>956</xmax>
      <ymax>774</ymax>
    </bndbox>
  </object>
  <object>
    <name>rider</name>
    <bndbox>
      <xmin>711</xmin>
      <ymin>680</ymin>
      <xmax>741</xmax>
      <ymax>743</ymax>
    </bndbox>
  </object>
  <object>
    <name>vehicle</name>
    <bndbox>
      <xmin>924</xmin>
      <ymin>685</ymin>
      <xmax>982</xmax>
      <ymax>742</ymax>
    </bndbox>
  </object>
</annotation>
