<?xml version="1.0" encoding="utf-8"?>
<annotation>
  <filename>All/Cityscape_03.mp4/Cityscape_03.mp4_01799.jpg</filename>
  <size>
    <width>1920</width>
    <height>1080</height>
    <depth>3</depth>
  </size>
  <object>
    <name>vehicle</name>
    <bndbox>
      <xmin>1312</xmin>
      <ymin>708</ymin>
      <xmax>1342</xmax>
      <ymax>737</ymax>
    </bndbox>
  </object>
  <object>
    <name>pedestrian</name>
    <bndbox>
      <xmin>1537</xmin>
      <ymin>670</ymin>
      <xmax>1569</xmax>
      <ymax>761</ymax>
    </bndbox>
  </object>
  <object>
    <name>vehicle</name>
    <bndbox>
      <xmin>1395</xmin>
      <ymin>702</ymin>
      <xmax>1429</xmax>
      <ymax>732</ymax>
    </bndbox>
  </object>
  <object>
    <name>vehicle</name>
    <bndbox>
      <xmin>1219</xmin>
      <ymin>704</ymin>
      <xmax>1283</xmax>
      <ymax>731</ymax>
    </bndbox>
  </object>
  <object>
    <name>vehicle</name>
    <bndbox>
      <xmin>982</xmin>
      <ymin>715</ymin>
      <xmax>1045</xmax>
      <ymax>740</ymax>
    </bndbox>
  </object>
  <object>
    <name>vehicle</name>
    <bndbox>
      <xmin>1453</xmin>
      <ymin>701</ymin>
      <xmax>1524</xmax>
      <ymax>733</ymax>
    </bndbox>
  </object>
  <object>
    <name>vehicle</name>
    <bndbox>
      <xmin>1357</xmin>
      <ymin>703</ymin>
      <xmax>1400</xmax>
      <ymax>736</ymax>
    </bndbox>
  </object>
  <object>
    <name>pedestrian</name>
    <bndbox>
      <xmin>1</xmin>
      <ymin>604</ymin>
      <xmax>72</xmax>
      <ymax>785</ymax>
    </bndbox>
  </object>
  <object>
    <name>vehicle</name>
    <bndbox>
      <xmin>1047</xmin>
      <ymin>714</ymin>
      <xmax>1096</xmax>
      <ymax>741</ymax>
    </bndbox>
  </object>
  <object>
    <name>vehicle</name>
    <bndbox>
      <xmin>789</xmin>
      <ymin>686</ymin>
      <xmax>980</xmax>
      <ymax>848</ymax>
    </bndbox>
  </object>
</annotation>
