<?xml version="1.0" encoding="utf-8"?>
<annotation>
  <filename>All/Cityscape_02.mp4/Cityscape_02.mp4_04863.jpg</filename>
  <size>
    <width>1920</width>
    <height>1080</height>
    <depth>3</depth>
  </size>
  <object>
    <name>rider</name>
    <bndbox>
      <xmin>1046</xmin>
      <ymin>671</ymin>
      <xmax>1091</xmax>
      <ymax>773</ymax>
    </bndbox>
  </object>
  <object>
    <name>rider</name>
    <bndbox>
      <xmin>1178</xmin>
      <ymin>663</ymin>
      <xmax>1225</xmax>
      <ymax>764</ymax>
    </bndbox>
  </object>
  <object>
    <name>vehicle</name>
    <bndbox>
      <xmin>533</xmin>
      <ymin>604</ymin>
      <xmax>1082</xmax>
      <ymax>1019</ymax>
    </bndbox>
  </object>
  <object>
    <name>rider</name>
    <bndbox>
      <xmin>438</xmin>
      <ymin>621</ymin>
      <xmax>572</xmax>
      <ymax>956</ymax>
    </bndbox>
  </object>
  <object>
    <name>rider</name>
    <bndbox>
      <xmin>1204</xmin>
      <ymin>626</ymin>
      <xmax>1356</xmax>
      <ymax>947</ymax>
    </bndbox>
  </object>
  <object>
    <name>vehicle</name>
    <bndbox>
      <xmin>1100</xmin>
      <ymin>681</ymin>
      <xmax>1168</xmax>
      <ymax>714</ymax>
    </bndbox>
  </object>
  <object>
    <name>vehicle</name>
    <bndbox>
      <xmin>72</xmin>
      <ymin>635</ymin>
      <xmax>568</xmax>
      <ymax>918</ymax>
    </bndbox>
  </object>
  <object>
    <name>rider</name>
    <bndbox>
      <xmin>1132</xmin>
      <ymin>659</ymin>
      <xmax>1217</xmax>
      <ymax>832</ymax>
    </bndbox>
  </object>
  <object>
    <name>rider</name>
    <bndbox>
      <xmin>1661</xmin>
      <ymin>435</ymin>
      <xmax>1920</xmax>
      <ymax>1080</ymax>
    </bndbox>
  </object>
</annotation>
