<?xml version="1.0" encoding="utf-8"?>
<annotation>
  <filename>All/Cityscape_02.mp4/Cityscape_02.mp4_01701.jpg</filename>
  <size>
    <width>1920</width>
    <height>1080</height>
    <depth>3</depth>
  </size>
  <object>
    <name>rider</name>
    <bndbox>
      <xmin>1037</xmin>
      <ymin>676</ymin>
      <xmax>1064</xmax>
      <ymax>738</ymax>
    </bndbox>
  </object>
  <object>
    <name>vehicle</name>
    <bndbox>
      <xmin>445</xmin>
      <ymin>670</ymin>
      <xmax>591</xmax>
      <ymax>757</ymax>
    </bndbox>
  </object>
  <object>
    <name>rider</name>
    <bndbox>
      <xmin>1104</xmin>
      <ymin>661</ymin>
      <xmax>1164</xmax>
      <ymax>820</ymax>
    </bndbox>
  </object>
  <object>
    <name>vehicle</name>
    <bndbox>
      <xmin>786</xmin>
      <ymin>670</ymin>
      <xmax>1045</xmax>
      <ymax>876</ymax>
    </bndbox>
  </object>
  <object>
    <name>rider</name>
    <bndbox>
      <xmin>1079</xmin>
      <ymin>671</ymin>
      <xmax>1122</xmax>
      <ymax>791</ymax>
    </bndbox>
  </object>
  <object>
    <name>vehicle</name>
    <bndbox>
      <xmin>576</xmin>
      <ymin>666</ymin>
      <xmax>786</xmax>
      <ymax>817</ymax>
    </bndbox>
  </object>
  <object>
    <name>vehicle</name>
    <bndbox>
      <xmin>0</xmin>
      <ymin>325</ymin>
      <xmax>421</xmax>
      <ymax>892</ymax>
    </bndbox>
  </object>
</annotation>
