<?xml version="1.0" encoding="utf-8"?>
<annotation>
  <filename>All/Cityscape_02.mp4/Cityscape_02.mp4_04845.jpg</filename>
  <size>
    <width>1920</width>
    <height>1080</height>
    <depth>3</depth>
  </size>
  <object>
    <name>rider</name>
    <bndbox>
      <xmin>1062</xmin>
      <ymin>671</ymin>
      <xmax>1114</xmax>
      <ymax>790</ymax>
    </bndbox>
  </object>
  <object>
    <name>pedestrian</name>
    <bndbox>
      <xmin>1769</xmin>
      <ymin>497</ymin>
      <xmax>1920</xmax>
      <ymax>979</ymax>
    </bndbox>
  </object>
  <object>
    <name>vehicle</name>
    <bndbox>
      <xmin>534</xmin>
      <ymin>605</ymin>
      <xmax>1084</xmax>
      <ymax>1022</ymax>
    </bndbox>
  </object>
  <object>
    <name>rider</name>
    <bndbox>
      <xmin>1</xmin>
      <ymin>511</ymin>
      <xmax>299</xmax>
      <ymax>1080</ymax>
    </bndbox>
  </object>
  <object>
    <name>rider</name>
    <bndbox>
      <xmin>1387</xmin>
      <ymin>557</ymin>
      <xmax>1719</xmax>
      <ymax>1067</ymax>
    </bndbox>
  </object>
  <object>
    <name>vehicle</name>
    <bndbox>
      <xmin>74</xmin>
      <ymin>634</ymin>
      <xmax>570</xmax>
      <ymax>915</ymax>
    </bndbox>
  </object>
  <object>
    <name>rider</name>
    <bndbox>
      <xmin>1183</xmin>
      <ymin>644</ymin>
      <xmax>1297</xmax>
      <ymax>885</ymax>
    </bndbox>
  </object>
</annotation>
