<?xml version="1.0" encoding="utf-8"?>
<annotation>
  <filename>All/Cityscape_01.mp4/Cityscape_01.mp4_04817.jpg</filename>
  <size>
    <width>1920</width>
    <height>1080</height>
    <depth>3</depth>
  </size>
  <object>
    <name>vehicle</name>
    <bndbox>
      <xmin>518</xmin>
      <ymin>574</ymin>
      <xmax>661</xmax>
      <ymax>665</ymax>
    </bndbox>
  </object>
  <object>
    <name>vehicle</name>
    <bndbox>
      <xmin>876</xmin>
      <ymin>587</ymin>
      <xmax>925</xmax>
      <ymax>624</ymax>
    </bndbox>
  </object>
  <object>
    <name>rider</name>
    <bndbox>
      <xmin>528</xmin>
      <ymin>563</ymin>
      <xmax>593</xmax>
      <ymax>701</ymax>
    </bndbox>
  </object>
  <object>
    <name>vehicle</name>
    <bndbox>
      <xmin>1068</xmin>
      <ymin>574</ymin>
      <xmax>1169</xmax>
      <ymax>667</ymax>
    </bndbox>
  </object>
  <object>
    <name>vehicle</name>
    <bndbox>
      <xmin>1320</xmin>
      <ymin>587</ymin>
      <xmax>1571</xmax>
      <ymax>725</ymax>
    </bndbox>
  </object>
  <object>
    <name>rider</name>
    <bndbox>
      <xmin>779</xmin>
      <ymin>577</ymin>
      <xmax>810</xmax>
      <ymax>637</ymax>
    </bndbox>
  </object>
  <object>
    <name>rider</name>
    <bndbox>
      <xmin>1217</xmin>
      <ymin>580</ymin>
      <xmax>1305</xmax>
      <ymax>668</ymax>
    </bndbox>
  </object>
  <object>
    <name>vehicle</name>
    <bndbox>
      <xmin>798</xmin>
      <ymin>574</ymin>
      <xmax>889</xmax>
      <ymax>651</ymax>
    </bndbox>
  </object>
  <object>
    <name>vehicle</name>
    <bndbox>
      <xmin>918</xmin>
      <ymin>575</ymin>
      <xmax>1040</xmax>
      <ymax>684</ymax>
    </bndbox>
  </object>
</annotation>
