<?xml version="1.0" encoding="utf-8"?>
<annotation>
  <filename>All/Cityscape_01.mp4/Cityscape_01.mp4_04377.jpg</filename>
  <size>
    <width>1920</width>
    <height>1080</height>
    <depth>3</depth>
  </size>
  <object>
    <name>vehicle</name>
    <bndbox>
      <xmin>1028</xmin>
      <ymin>584</ymin>
      <xmax>1087</xmax>
      <ymax>635</ymax>
    </bndbox>
  </object>
  <object>
    <name>vehicle</name>
    <bndbox>
      <xmin>764</xmin>
      <ymin>587</ymin>
      <xmax>837</xmax>
      <ymax>637</ymax>
    </bndbox>
  </object>
  <object>
    <name>pedestrian</name>
    <bndbox>
      <xmin>1630</xmin>
      <ymin>567</ymin>
      <xmax>1680</xmax>
      <ymax>742</ymax>
    </bndbox>
  </object>
  <object>
    <name>vehicle</name>
    <bndbox>
      <xmin>493</xmin>
      <ymin>567</ymin>
      <xmax>636</xmax>
      <ymax>666</ymax>
    </bndbox>
  </object>
  <object>
    <name>vehicle</name>
    <bndbox>
      <xmin>690</xmin>
      <ymin>584</ymin>
      <xmax>773</xmax>
      <ymax>641</ymax>
    </bndbox>
  </object>
  <object>
    <name>vehicle</name>
    <bndbox>
      <xmin>899</xmin>
      <ymin>568</ymin>
      <xmax>1052</xmax>
      <ymax>707</ymax>
    </bndbox>
  </object>
  <object>
    <name>vehicle</name>
    <bndbox>
      <xmin>1135</xmin>
      <ymin>589</ymin>
      <xmax>1268</xmax>
      <ymax>678</ymax>
    </bndbox>
  </object>
</annotation>
