<?xml version="1.0" encoding="utf-8"?>
<annotation>
  <filename>All/Cityscape_01.mp4/Cityscape_01.mp4_05072.jpg</filename>
  <size>
    <width>1920</width>
    <height>1080</height>
    <depth>3</depth>
  </size>
  <object>
    <name>vehicle</name>
    <bndbox>
      <xmin>118</xmin>
      <ymin>575</ymin>
      <xmax>241</xmax>
      <ymax>641</ymax>
    </bndbox>
  </object>
  <object>
    <name>vehicle</name>
    <bndbox>
      <xmin>1317</xmin>
      <ymin>600</ymin>
      <xmax>1506</xmax>
      <ymax>670</ymax>
    </bndbox>
  </object>
  <object>
    <name>rider</name>
    <bndbox>
      <xmin>651</xmin>
      <ymin>585</ymin>
      <xmax>697</xmax>
      <ymax>649</ymax>
    </bndbox>
  </object>
  <object>
    <name>vehicle</name>
    <bndbox>
      <xmin>797</xmin>
      <ymin>589</ymin>
      <xmax>836</xmax>
      <ymax>624</ymax>
    </bndbox>
  </object>
  <object>
    <name>vehicle</name>
    <bndbox>
      <xmin>852</xmin>
      <ymin>586</ymin>
      <xmax>877</xmax>
      <ymax>612</ymax>
    </bndbox>
  </object>
  <object>
    <name>rider</name>
    <bndbox>
      <xmin>1591</xmin>
      <ymin>594</ymin>
      <xmax>1651</xmax>
      <ymax>666</ymax>
    </bndbox>
  </object>
  <object>
    <name>vehicle</name>
    <bndbox>
      <xmin>927</xmin>
      <ymin>582</ymin>
      <xmax>1026</xmax>
      <ymax>671</ymax>
    </bndbox>
  </object>
  <object>
    <name>vehicle</name>
    <bndbox>
      <xmin>1060</xmin>
      <ymin>602</ymin>
      <xmax>1119</xmax>
      <ymax>649</ymax>
    </bndbox>
  </object>
</annotation>
