<?xml version="1.0" encoding="utf-8"?>
<annotation>
  <filename>All/Cityscape_06.mp4/Cityscape_06.mp4_01368.jpg</filename>
  <size>
    <width>1920</width>
    <height>1080</height>
    <depth>3</depth>
  </size>
  <object>
    <name>vehicle</name>
    <bndbox>
      <xmin>1346</xmin>
      <ymin>604</ymin>
      <xmax>1520</xmax>
      <ymax>727</ymax>
    </bndbox>
  </object>
  <object>
    <name>vehicle</name>
    <bndbox>
      <xmin>1546</xmin>
      <ymin>573</ymin>
      <xmax>1920</xmax>
      <ymax>819</ymax>
    </bndbox>
  </object>
  <object>
    <name>vehicle</name>
    <bndbox>
      <xmin>495</xmin>
      <ymin>623</ymin>
      <xmax>649</xmax>
      <ymax>684</ymax>
    </bndbox>
  </object>
  <object>
    <name>vehicle</name>
    <bndbox>
      <xmin>241</xmin>
      <ymin>570</ymin>
      <xmax>512</xmax>
      <ymax>743</ymax>
    </bndbox>
  </object>
  <object>
    <name>vehicle</name>
    <bndbox>
      <xmin>0</xmin>
      <ymin>589</ymin>
      <xmax>290</xmax>
      <ymax>784</ymax>
    </bndbox>
  </object>
  <object>
    <name>vehicle</name>
    <bndbox>
      <xmin>99</xmin>
      <ymin>596</ymin>
      <xmax>364</xmax>
      <ymax>754</ymax>
    </bndbox>
  </object>
  <object>
    <name>vehicle</name>
    <bndbox>
      <xmin>465</xmin>
      <ymin>609</ymin>
      <xmax>589</xmax>
      <ymax>680</ymax>
    </bndbox>
  </object>
  <object>
    <name>vehicle</name>
    <bndbox>
      <xmin>641</xmin>
      <ymin>623</ymin>
      <xmax>799</xmax>
      <ymax>682</ymax>
    </bndbox>
  </object>
</annotation>
