<?xml version="1.0" encoding="utf-8"?>
<annotation>
  <filename>All/Cityscape_06.mp4/Cityscape_06.mp4_01626.jpg</filename>
  <size>
    <width>1920</width>
    <height>1080</height>
    <depth>3</depth>
  </size>
  <object>
    <name>vehicle</name>
    <bndbox>
      <xmin>30</xmin>
      <ymin>584</ymin>
      <xmax>239</xmax>
      <ymax>712</ymax>
    </bndbox>
  </object>
  <object>
    <name>vehicle</name>
    <bndbox>
      <xmin>232</xmin>
      <ymin>590</ymin>
      <xmax>506</xmax>
      <ymax>716</ymax>
    </bndbox>
  </object>
  <object>
    <name>vehicle</name>
    <bndbox>
      <xmin>359</xmin>
      <ymin>590</ymin>
      <xmax>608</xmax>
      <ymax>710</ymax>
    </bndbox>
  </object>
  <object>
    <name>vehicle</name>
    <bndbox>
      <xmin>653</xmin>
      <ymin>595</ymin>
      <xmax>761</xmax>
      <ymax>684</ymax>
    </bndbox>
  </object>
</annotation>
