<?xml version="1.0" encoding="utf-8"?>
<annotation>
  <filename>All/Cityscape_06.mp4/Cityscape_06.mp4_01278.jpg</filename>
  <size>
    <width>1920</width>
    <height>1080</height>
    <depth>3</depth>
  </size>
  <object>
    <name>vehicle</name>
    <bndbox>
      <xmin>314</xmin>
      <ymin>546</ymin>
      <xmax>655</xmax>
      <ymax>744</ymax>
    </bndbox>
  </object>
  <object>
    <name>vehicle</name>
    <bndbox>
      <xmin>587</xmin>
      <ymin>586</ymin>
      <xmax>801</xmax>
      <ymax>721</ymax>
    </bndbox>
  </object>
  <object>
    <name>vehicle</name>
    <bndbox>
      <xmin>1598</xmin>
      <ymin>581</ymin>
      <xmax>1920</xmax>
      <ymax>944</ymax>
    </bndbox>
  </object>
  <object>
    <name>vehicle</name>
    <bndbox>
      <xmin>880</xmin>
      <ymin>619</ymin>
      <xmax>1032</xmax>
      <ymax>681</ymax>
    </bndbox>
  </object>
  <object>
    <name>vehicle</name>
    <bndbox>
      <xmin>723</xmin>
      <ymin>602</ymin>
      <xmax>902</xmax>
      <ymax>704</ymax>
    </bndbox>
  </object>
</annotation>
