<?xml version="1.0" encoding="utf-8"?>
<annotation>
  <filename>All/Cityscape_06.mp4/Cityscape_06.mp4_08043.jpg</filename>
  <size>
    <width>1920</width>
    <height>1080</height>
    <depth>3</depth>
  </size>
  <object>
    <name>rider</name>
    <bndbox>
      <xmin>1062</xmin>
      <ymin>632</ymin>
      <xmax>1084</xmax>
      <ymax>685</ymax>
    </bndbox>
  </object>
  <object>
    <name>pedestrian</name>
    <bndbox>
      <xmin>1498</xmin>
      <ymin>641</ymin>
      <xmax>1544</xmax>
      <ymax>747</ymax>
    </bndbox>
  </object>
  <object>
    <name>pedestrian</name>
    <bndbox>
      <xmin>1759</xmin>
      <ymin>583</ymin>
      <xmax>1812</xmax>
      <ymax>724</ymax>
    </bndbox>
  </object>
  <object>
    <name>pedestrian</name>
    <bndbox>
      <xmin>1490</xmin>
      <ymin>608</ymin>
      <xmax>1542</xmax>
      <ymax>717</ymax>
    </bndbox>
  </object>
  <object>
    <name>pedestrian</name>
    <bndbox>
      <xmin>1737</xmin>
      <ymin>575</ymin>
      <xmax>1781</xmax>
      <ymax>720</ymax>
    </bndbox>
  </object>
  <object>
    <name>rider</name>
    <bndbox>
      <xmin>1026</xmin>
      <ymin>636</ymin>
      <xmax>1047</xmax>
      <ymax>682</ymax>
    </bndbox>
  </object>
  <object>
    <name>vehicle</name>
    <bndbox>
      <xmin>244</xmin>
      <ymin>569</ymin>
      <xmax>667</xmax>
      <ymax>840</ymax>
    </bndbox>
  </object>
  <object>
    <name>pedestrian</name>
    <bndbox>
      <xmin>1730</xmin>
      <ymin>601</ymin>
      <xmax>1792</xmax>
      <ymax>769</ymax>
    </bndbox>
  </object>
  <object>
    <name>rider</name>
    <bndbox>
      <xmin>1094</xmin>
      <ymin>628</ymin>
      <xmax>1118</xmax>
      <ymax>682</ymax>
    </bndbox>
  </object>
  <object>
    <name>vehicle</name>
    <bndbox>
      <xmin>673</xmin>
      <ymin>585</ymin>
      <xmax>1033</xmax>
      <ymax>853</ymax>
    </bndbox>
  </object>
  <object>
    <name>pedestrian</name>
    <bndbox>
      <xmin>1688</xmin>
      <ymin>581</ymin>
      <xmax>1726</xmax>
      <ymax>729</ymax>
    </bndbox>
  </object>
</annotation>
