<?xml version="1.0" encoding="utf-8"?>
<annotation>
  <filename>All/Cityscape_06.mp4/Cityscape_06.mp4_07322.jpg</filename>
  <size>
    <width>1920</width>
    <height>1080</height>
    <depth>3</depth>
  </size>
  <object>
    <name>rider</name>
    <bndbox>
      <xmin>275</xmin>
      <ymin>627</ymin>
      <xmax>321</xmax>
      <ymax>694</ymax>
    </bndbox>
  </object>
  <object>
    <name>vehicle</name>
    <bndbox>
      <xmin>642</xmin>
      <ymin>633</ymin>
      <xmax>695</xmax>
      <ymax>676</ymax>
    </bndbox>
  </object>
  <object>
    <name>vehicle</name>
    <bndbox>
      <xmin>112</xmin>
      <ymin>603</ymin>
      <xmax>263</xmax>
      <ymax>709</ymax>
    </bndbox>
  </object>
  <object>
    <name>vehicle</name>
    <bndbox>
      <xmin>807</xmin>
      <ymin>627</ymin>
      <xmax>866</xmax>
      <ymax>682</ymax>
    </bndbox>
  </object>
  <object>
    <name>rider</name>
    <bndbox>
      <xmin>1038</xmin>
      <ymin>630</ymin>
      <xmax>1070</xmax>
      <ymax>678</ymax>
    </bndbox>
  </object>
  <object>
    <name>pedestrian</name>
    <bndbox>
      <xmin>1422</xmin>
      <ymin>594</ymin>
      <xmax>1471</xmax>
      <ymax>719</ymax>
    </bndbox>
  </object>
  <object>
    <name>vehicle</name>
    <bndbox>
      <xmin>556</xmin>
      <ymin>630</ymin>
      <xmax>629</xmax>
      <ymax>683</ymax>
    </bndbox>
  </object>
  <object>
    <name>rider</name>
    <bndbox>
      <xmin>1095</xmin>
      <ymin>619</ymin>
      <xmax>1126</xmax>
      <ymax>697</ymax>
    </bndbox>
  </object>
  <object>
    <name>rider</name>
    <bndbox>
      <xmin>371</xmin>
      <ymin>633</ymin>
      <xmax>420</xmax>
      <ymax>682</ymax>
    </bndbox>
  </object>
  <object>
    <name>vehicle</name>
    <bndbox>
      <xmin>836</xmin>
      <ymin>610</ymin>
      <xmax>985</xmax>
      <ymax>735</ymax>
    </bndbox>
  </object>
  <object>
    <name>vehicle</name>
    <bndbox>
      <xmin>715</xmin>
      <ymin>637</ymin>
      <xmax>758</xmax>
      <ymax>669</ymax>
    </bndbox>
  </object>
  <object>
    <name>vehicle</name>
    <bndbox>
      <xmin>1</xmin>
      <ymin>525</ymin>
      <xmax>344</xmax>
      <ymax>991</ymax>
    </bndbox>
  </object>
  <object>
    <name>rider</name>
    <bndbox>
      <xmin>984</xmin>
      <ymin>632</ymin>
      <xmax>1004</xmax>
      <ymax>675</ymax>
    </bndbox>
  </object>
</annotation>
