<?xml version="1.0" encoding="utf-8"?>
<annotation>
  <filename>All/Cityscape_06.mp4/Cityscape_06.mp4_00235.jpg</filename>
  <size>
    <width>1920</width>
    <height>1080</height>
    <depth>3</depth>
  </size>
  <object>
    <name>vehicle</name>
    <bndbox>
      <xmin>172</xmin>
      <ymin>555</ymin>
      <xmax>299</xmax>
      <ymax>711</ymax>
    </bndbox>
  </object>
  <object>
    <name>vehicle</name>
    <bndbox>
      <xmin>1525</xmin>
      <ymin>625</ymin>
      <xmax>1668</xmax>
      <ymax>752</ymax>
    </bndbox>
  </object>
  <object>
    <name>vehicle</name>
    <bndbox>
      <xmin>1658</xmin>
      <ymin>604</ymin>
      <xmax>1849</xmax>
      <ymax>700</ymax>
    </bndbox>
  </object>
</annotation>
