<?xml version="1.0" encoding="utf-8"?>
<annotation>
  <filename>All/Cityscape_06.mp4/Cityscape_06.mp4_02383.jpg</filename>
  <size>
    <width>1920</width>
    <height>1080</height>
    <depth>3</depth>
  </size>
  <object>
    <name>vehicle</name>
    <bndbox>
      <xmin>666</xmin>
      <ymin>633</ymin>
      <xmax>727</xmax>
      <ymax>671</ymax>
    </bndbox>
  </object>
  <object>
    <name>vehicle</name>
    <bndbox>
      <xmin>745</xmin>
      <ymin>610</ymin>
      <xmax>921</xmax>
      <ymax>745</ymax>
    </bndbox>
  </object>
  <object>
    <name>vehicle</name>
    <bndbox>
      <xmin>1182</xmin>
      <ymin>636</ymin>
      <xmax>1312</xmax>
      <ymax>728</ymax>
    </bndbox>
  </object>
  <object>
    <name>vehicle</name>
    <bndbox>
      <xmin>596</xmin>
      <ymin>630</ymin>
      <xmax>664</xmax>
      <ymax>681</ymax>
    </bndbox>
  </object>
  <object>
    <name>rider</name>
    <bndbox>
      <xmin>1</xmin>
      <ymin>611</ymin>
      <xmax>24</xmax>
      <ymax>717</ymax>
    </bndbox>
  </object>
  <object>
    <name>vehicle</name>
    <bndbox>
      <xmin>924</xmin>
      <ymin>616</ymin>
      <xmax>997</xmax>
      <ymax>688</ymax>
    </bndbox>
  </object>
  <object>
    <name>vehicle</name>
    <bndbox>
      <xmin>455</xmin>
      <ymin>628</ymin>
      <xmax>538</xmax>
      <ymax>675</ymax>
    </bndbox>
  </object>
  <object>
    <name>vehicle</name>
    <bndbox>
      <xmin>23</xmin>
      <ymin>605</ymin>
      <xmax>185</xmax>
      <ymax>705</ymax>
    </bndbox>
  </object>
  <object>
    <name>vehicle</name>
    <bndbox>
      <xmin>1016</xmin>
      <ymin>605</ymin>
      <xmax>1065</xmax>
      <ymax>658</ymax>
    </bndbox>
  </object>
  <object>
    <name>vehicle</name>
    <bndbox>
      <xmin>523</xmin>
      <ymin>631</ymin>
      <xmax>582</xmax>
      <ymax>666</ymax>
    </bndbox>
  </object>
  <object>
    <name>pedestrian</name>
    <bndbox>
      <xmin>182</xmin>
      <ymin>609</ymin>
      <xmax>202</xmax>
      <ymax>672</ymax>
    </bndbox>
  </object>
</annotation>
