<?xml version="1.0" encoding="utf-8"?>
<annotation>
  <filename>All/Cityscape_06.mp4/Cityscape_06.mp4_07619.jpg</filename>
  <size>
    <width>1920</width>
    <height>1080</height>
    <depth>3</depth>
  </size>
  <object>
    <name>vehicle</name>
    <bndbox>
      <xmin>1</xmin>
      <ymin>496</ymin>
      <xmax>255</xmax>
      <ymax>670</ymax>
    </bndbox>
  </object>
  <object>
    <name>pedestrian</name>
    <bndbox>
      <xmin>1705</xmin>
      <ymin>587</ymin>
      <xmax>1774</xmax>
      <ymax>771</ymax>
    </bndbox>
  </object>
  <object>
    <name>pedestrian</name>
    <bndbox>
      <xmin>1491</xmin>
      <ymin>593</ymin>
      <xmax>1547</xmax>
      <ymax>722</ymax>
    </bndbox>
  </object>
  <object>
    <name>rider</name>
    <bndbox>
      <xmin>1042</xmin>
      <ymin>604</ymin>
      <xmax>1083</xmax>
      <ymax>697</ymax>
    </bndbox>
  </object>
  <object>
    <name>pedestrian</name>
    <bndbox>
      <xmin>1836</xmin>
      <ymin>579</ymin>
      <xmax>1895</xmax>
      <ymax>778</ymax>
    </bndbox>
  </object>
  <object>
    <name>vehicle</name>
    <bndbox>
      <xmin>1132</xmin>
      <ymin>570</ymin>
      <xmax>1281</xmax>
      <ymax>735</ymax>
    </bndbox>
  </object>
  <object>
    <name>vehicle</name>
    <bndbox>
      <xmin>808</xmin>
      <ymin>592</ymin>
      <xmax>1025</xmax>
      <ymax>777</ymax>
    </bndbox>
  </object>
  <object>
    <name>pedestrian</name>
    <bndbox>
      <xmin>1901</xmin>
      <ymin>583</ymin>
      <xmax>1920</xmax>
      <ymax>766</ymax>
    </bndbox>
  </object>
  <object>
    <name>rider</name>
    <bndbox>
      <xmin>1024</xmin>
      <ymin>610</ymin>
      <xmax>1050</xmax>
      <ymax>665</ymax>
    </bndbox>
  </object>
  <object>
    <name>vehicle</name>
    <bndbox>
      <xmin>1262</xmin>
      <ymin>592</ymin>
      <xmax>1478</xmax>
      <ymax>775</ymax>
    </bndbox>
  </object>
</annotation>
