<?xml version="1.0" encoding="utf-8"?>
<annotation>
  <filename>All/Cityscape_06.mp4/Cityscape_06.mp4_07058.jpg</filename>
  <size>
    <width>1920</width>
    <height>1080</height>
    <depth>3</depth>
  </size>
  <object>
    <name>rider</name>
    <bndbox>
      <xmin>1212</xmin>
      <ymin>613</ymin>
      <xmax>1315</xmax>
      <ymax>722</ymax>
    </bndbox>
  </object>
  <object>
    <name>vehicle</name>
    <bndbox>
      <xmin>808</xmin>
      <ymin>611</ymin>
      <xmax>867</xmax>
      <ymax>666</ymax>
    </bndbox>
  </object>
  <object>
    <name>rider</name>
    <bndbox>
      <xmin>147</xmin>
      <ymin>610</ymin>
      <xmax>193</xmax>
      <ymax>689</ymax>
    </bndbox>
  </object>
  <object>
    <name>vehicle</name>
    <bndbox>
      <xmin>826</xmin>
      <ymin>604</ymin>
      <xmax>987</xmax>
      <ymax>746</ymax>
    </bndbox>
  </object>
  <object>
    <name>vehicle</name>
    <bndbox>
      <xmin>381</xmin>
      <ymin>584</ymin>
      <xmax>670</xmax>
      <ymax>783</ymax>
    </bndbox>
  </object>
  <object>
    <name>rider</name>
    <bndbox>
      <xmin>1246</xmin>
      <ymin>615</ymin>
      <xmax>1367</xmax>
      <ymax>736</ymax>
    </bndbox>
  </object>
</annotation>
