<?xml version="1.0" encoding="utf-8"?>
<annotation>
  <filename>All/Cityscape_06.mp4/Cityscape_06.mp4_08201.jpg</filename>
  <size>
    <width>1920</width>
    <height>1080</height>
    <depth>3</depth>
  </size>
  <object>
    <name>pedestrian</name>
    <bndbox>
      <xmin>1650</xmin>
      <ymin>582</ymin>
      <xmax>1703</xmax>
      <ymax>724</ymax>
    </bndbox>
  </object>
  <object>
    <name>vehicle</name>
    <bndbox>
      <xmin>304</xmin>
      <ymin>597</ymin>
      <xmax>681</xmax>
      <ymax>827</ymax>
    </bndbox>
  </object>
  <object>
    <name>vehicle</name>
    <bndbox>
      <xmin>782</xmin>
      <ymin>626</ymin>
      <xmax>883</xmax>
      <ymax>712</ymax>
    </bndbox>
  </object>
  <object>
    <name>vehicle</name>
    <bndbox>
      <xmin>1082</xmin>
      <ymin>642</ymin>
      <xmax>1116</xmax>
      <ymax>676</ymax>
    </bndbox>
  </object>
  <object>
    <name>vehicle</name>
    <bndbox>
      <xmin>874</xmin>
      <ymin>616</ymin>
      <xmax>1073</xmax>
      <ymax>784</ymax>
    </bndbox>
  </object>
</annotation>
