<?xml version="1.0" encoding="utf-8"?>
<annotation>
  <filename>All/Cityscape_06.mp4/Cityscape_06.mp4_00474.jpg</filename>
  <size>
    <width>1920</width>
    <height>1080</height>
    <depth>3</depth>
  </size>
  <object>
    <name>vehicle</name>
    <bndbox>
      <xmin>666</xmin>
      <ymin>630</ymin>
      <xmax>773</xmax>
      <ymax>702</ymax>
    </bndbox>
  </object>
  <object>
    <name>rider</name>
    <bndbox>
      <xmin>1049</xmin>
      <ymin>622</ymin>
      <xmax>1072</xmax>
      <ymax>696</ymax>
    </bndbox>
  </object>
  <object>
    <name>vehicle</name>
    <bndbox>
      <xmin>1301</xmin>
      <ymin>571</ymin>
      <xmax>1597</xmax>
      <ymax>809</ymax>
    </bndbox>
  </object>
  <object>
    <name>vehicle</name>
    <bndbox>
      <xmin>1156</xmin>
      <ymin>632</ymin>
      <xmax>1295</xmax>
      <ymax>737</ymax>
    </bndbox>
  </object>
  <object>
    <name>vehicle</name>
    <bndbox>
      <xmin>1020</xmin>
      <ymin>637</ymin>
      <xmax>1054</xmax>
      <ymax>670</ymax>
    </bndbox>
  </object>
  <object>
    <name>vehicle</name>
    <bndbox>
      <xmin>642</xmin>
      <ymin>637</ymin>
      <xmax>703</xmax>
      <ymax>683</ymax>
    </bndbox>
  </object>
  <object>
    <name>vehicle</name>
    <bndbox>
      <xmin>718</xmin>
      <ymin>632</ymin>
      <xmax>766</xmax>
      <ymax>678</ymax>
    </bndbox>
  </object>
  <object>
    <name>vehicle</name>
    <bndbox>
      <xmin>947</xmin>
      <ymin>635</ymin>
      <xmax>975</xmax>
      <ymax>663</ymax>
    </bndbox>
  </object>
</annotation>
