<?xml version="1.0" encoding="utf-8"?>
<annotation>
  <filename>All/Cityscape_06.mp4/Cityscape_06.mp4_02942.jpg</filename>
  <size>
    <width>1920</width>
    <height>1080</height>
    <depth>3</depth>
  </size>
  <object>
    <name>vehicle</name>
    <bndbox>
      <xmin>662</xmin>
      <ymin>554</ymin>
      <xmax>1200</xmax>
      <ymax>982</ymax>
    </bndbox>
  </object>
  <object>
    <name>pedestrian</name>
    <bndbox>
      <xmin>1083</xmin>
      <ymin>341</ymin>
      <xmax>1111</xmax>
      <ymax>397</ymax>
    </bndbox>
  </object>
  <object>
    <name>vehicle</name>
    <bndbox>
      <xmin>1158</xmin>
      <ymin>611</ymin>
      <xmax>1399</xmax>
      <ymax>780</ymax>
    </bndbox>
  </object>
  <object>
    <name>rider</name>
    <bndbox>
      <xmin>220</xmin>
      <ymin>613</ymin>
      <xmax>274</xmax>
      <ymax>668</ymax>
    </bndbox>
  </object>
  <object>
    <name>vehicle</name>
    <bndbox>
      <xmin>275</xmin>
      <ymin>560</ymin>
      <xmax>698</xmax>
      <ymax>855</ymax>
    </bndbox>
  </object>
  <object>
    <name>vehicle</name>
    <bndbox>
      <xmin>0</xmin>
      <ymin>625</ymin>
      <xmax>265</xmax>
      <ymax>1004</ymax>
    </bndbox>
  </object>
  <object>
    <name>vehicle</name>
    <bndbox>
      <xmin>1057</xmin>
      <ymin>488</ymin>
      <xmax>1259</xmax>
      <ymax>725</ymax>
    </bndbox>
  </object>
</annotation>
