<?xml version="1.0" encoding="utf-8"?>
<annotation>
  <filename>All/Cityscape_06.mp4/Cityscape_06.mp4_02454.jpg</filename>
  <size>
    <width>1920</width>
    <height>1080</height>
    <depth>3</depth>
  </size>
  <object>
    <name>vehicle</name>
    <bndbox>
      <xmin>535</xmin>
      <ymin>610</ymin>
      <xmax>642</xmax>
      <ymax>682</ymax>
    </bndbox>
  </object>
  <object>
    <name>vehicle</name>
    <bndbox>
      <xmin>570</xmin>
      <ymin>622</ymin>
      <xmax>617</xmax>
      <ymax>665</ymax>
    </bndbox>
  </object>
  <object>
    <name>vehicle</name>
    <bndbox>
      <xmin>692</xmin>
      <ymin>616</ymin>
      <xmax>754</xmax>
      <ymax>664</ymax>
    </bndbox>
  </object>
  <object>
    <name>vehicle</name>
    <bndbox>
      <xmin>837</xmin>
      <ymin>598</ymin>
      <xmax>983</xmax>
      <ymax>722</ymax>
    </bndbox>
  </object>
  <object>
    <name>vehicle</name>
    <bndbox>
      <xmin>319</xmin>
      <ymin>609</ymin>
      <xmax>483</xmax>
      <ymax>692</ymax>
    </bndbox>
  </object>
  <object>
    <name>pedestrian</name>
    <bndbox>
      <xmin>1101</xmin>
      <ymin>610</ymin>
      <xmax>1135</xmax>
      <ymax>680</ymax>
    </bndbox>
  </object>
  <object>
    <name>vehicle</name>
    <bndbox>
      <xmin>305</xmin>
      <ymin>613</ymin>
      <xmax>401</xmax>
      <ymax>681</ymax>
    </bndbox>
  </object>
  <object>
    <name>vehicle</name>
    <bndbox>
      <xmin>0</xmin>
      <ymin>610</ymin>
      <xmax>109</xmax>
      <ymax>701</ymax>
    </bndbox>
  </object>
  <object>
    <name>vehicle</name>
    <bndbox>
      <xmin>999</xmin>
      <ymin>589</ymin>
      <xmax>1043</xmax>
      <ymax>650</ymax>
    </bndbox>
  </object>
  <object>
    <name>vehicle</name>
    <bndbox>
      <xmin>92</xmin>
      <ymin>613</ymin>
      <xmax>233</xmax>
      <ymax>692</ymax>
    </bndbox>
  </object>
</annotation>
