<?xml version="1.0" encoding="utf-8"?>
<annotation>
  <filename>All/Fog_01.mp4/Fog_01.mp4_00801.jpg</filename>
  <size>
    <width>1920</width>
    <height>1080</height>
    <depth>3</depth>
  </size>
  <object>
    <name>vehicle</name>
    <bndbox>
      <xmin>217</xmin>
      <ymin>553</ymin>
      <xmax>571</xmax>
      <ymax>903</ymax>
    </bndbox>
  </object>
  <object>
    <name>vehicle</name>
    <bndbox>
      <xmin>1623</xmin>
      <ymin>564</ymin>
      <xmax>1919</xmax>
      <ymax>915</ymax>
    </bndbox>
  </object>
  <object>
    <name>pedestrian</name>
    <bndbox>
      <xmin>1344</xmin>
      <ymin>577</ymin>
      <xmax>1438</xmax>
      <ymax>868</ymax>
    </bndbox>
  </object>
</annotation>
