<?xml version="1.0" encoding="utf-8"?>
<annotation>
  <filename>All/Fog_01.mp4/Fog_01.mp4_02044.jpg</filename>
  <size>
    <width>1920</width>
    <height>1080</height>
    <depth>3</depth>
  </size>
  <object>
    <name>vehicle</name>
    <bndbox>
      <xmin>1082</xmin>
      <ymin>642</ymin>
      <xmax>1634</xmax>
      <ymax>942</ymax>
    </bndbox>
  </object>
  <object>
    <name>pedestrian</name>
    <bndbox>
      <xmin>1774</xmin>
      <ymin>548</ymin>
      <xmax>1890</xmax>
      <ymax>918</ymax>
    </bndbox>
  </object>
  <object>
    <name>vehicle</name>
    <bndbox>
      <xmin>92</xmin>
      <ymin>704</ymin>
      <xmax>377</xmax>
      <ymax>853</ymax>
    </bndbox>
  </object>
  <object>
    <name>pedestrian</name>
    <bndbox>
      <xmin>883</xmin>
      <ymin>591</ymin>
      <xmax>985</xmax>
      <ymax>942</ymax>
    </bndbox>
  </object>
</annotation>
